{
  "success": true,
  "timestamp": "2025-09-03T09:30:00Z",
  "currentPrice": 591.1648524317609,
  "dataSource": "Synthetic Historical",
  "regime": {
    "state": "TREND",
    "current": "TREND",
    "probability": 0.7759949774242596
  },
  "confidence": {
    "overall": 0.3654825434704736,
    "1m": 0.5,
    "5m": 0.5,
    "15m": 0.5,
    "1h": 0.5,
    "4h": 0.5,
    "1d": 0.5
  },
  "predictions": {
    "1m": {
      "direction": "NEUTRAL",
      "target": 591.16,
      "stop_loss": 591.16,
      "stopLoss": 591.16,
      "cone_upper": 591.89,
      "cone_lower": 590.44,
      "upperBound": 591.89,
      "lowerBound": 590.44,
      "confidence": 0.5
    },
    "5m": {
      "direction": "NEUTRAL",
      "target": 591.16,
      "stop_loss": 591.16,
      "stopLoss": 591.16,
      "cone_upper": 592.97,
      "cone_lower": 589.36,
      "upperBound": 592.97,
      "lowerBound": 589.36,
      "confidence": 0.5
    },
    "15m": {
      "direction": "NEUTRAL",
      "target": 591.16,
      "stop_loss": 591.16,
      "stopLoss": 591.16,
      "cone_upper": 594.77,
      "cone_lower": 587.56,
      "upperBound": 594.77,
      "lowerBound": 587.56,
      "confidence": 0.5
    },
    "1h": {
      "direction": "NEUTRAL",
      "target": 591.16,
      "stop_loss": 591.16,
      "stopLoss": 591.16,
      "cone_upper": 598.38,
      "cone_lower": 583.95,
      "upperBound": 598.38,
      "lowerBound": 583.95,
      "confidence": 0.5
    },
    "4h": {
      "direction": "NEUTRAL",
      "target": 591.16,
      "stop_loss": 591.16,
      "stopLoss": 591.16,
      "cone_upper": 605.6,
      "cone_lower": 576.73,
      "upperBound": 605.6,
      "lowerBound": 576.73,
      "confidence": 0.5
    },
    "1d": {
      "direction": "BULLISH",
      "target": 601.99,
      "stop_loss": 585.75,
      "stopLoss": 585.75,
      "cone_upper": 612.81,
      "cone_lower": 569.52,
      "upperBound": 612.81,
      "lowerBound": 569.52,
      "confidence": 0.5
    }
  },
  "forecasts": {
    "1m": {
      "direction": "NEUTRAL",
      "target": 591.16,
      "stop_loss": 591.16,
      "stopLoss": 591.16,
      "cone_upper": 591.89,
      "cone_lower": 590.44,
      "upperBound": 591.89,
      "lowerBound": 590.44,
      "confidence": 0.5
    },
    "5m": {
      "direction": "NEUTRAL",
      "target": 591.16,
      "stop_loss": 591.16,
      "stopLoss": 591.16,
      "cone_upper": 592.97,
      "cone_lower": 589.36,
      "upperBound": 592.97,
      "lowerBound": 589.36,
      "confidence": 0.5
    },
    "15m": {
      "direction": "NEUTRAL",
      "target": 591.16,
      "stop_loss": 591.16,
      "stopLoss": 591.16,
      "cone_upper": 594.77,
      "cone_lower": 587.56,
      "upperBound": 594.77,
      "lowerBound": 587.56,
      "confidence": 0.5
    },
    "1h": {
      "direction": "NEUTRAL",
      "target": 591.16,
      "stop_loss": 591.16,
      "stopLoss": 591.16,
      "cone_upper": 598.38,
      "cone_lower": 583.95,
      "upperBound": 598.38,
      "lowerBound": 583.95,
      "confidence": 0.5
    },
    "4h": {
      "direction": "NEUTRAL",
      "target": 591.16,
      "stop_loss": 591.16,
      "stopLoss": 591.16,
      "cone_upper": 605.6,
      "cone_lower": 576.73,
      "upperBound": 605.6,
      "lowerBound": 576.73,
      "confidence": 0.5
    },
    "1d": {
      "direction": "BULLISH",
      "target": 601.99,
      "stop_loss": 585.75,
      "stopLoss": 585.75,
      "cone_upper": 612.81,
      "cone_lower": 569.52,
      "upperBound": 612.81,
      "lowerBound": 569.52,
      "confidence": 0.5
    }
  },
  "forecast": {
    "expectedPrice": 594.7727220012889,
    "cone": {
      "upper80": 615.9662150302267,
      "upper60": 608.5971039009827,
      "median": 594.7727220012889,
      "lower40": 586.3725963949381,
      "lower20": 574.3084315419198
    },
    "directionalScore": 0.22243540432979023,
    "confidence": 0.3654825434704736,
    "signal": "NEUTRAL"
  },
  "optionTrade": {
    "side": null,
    "strike": 0,
    "expiry": 0,
    "targetDelta": 0,
    "entryPrice": 0,
    "targetExit": 0,
    "stopLoss": 0,
    "confidence": 0,
    "reasoning": "No clear directional edge",
    "greeks": {}
  },
  "option_recommendation": {
    "type": null,
    "strike": 0,
    "expiry": 0,
    "stop_loss": 0,
    "confidence": 0.3654825434704736,
    "greeks": {}
  },
  "kellySizing": 0.1,
  "kelly_size": 0.1,
  "flowMetrics": {
    "gex": 16.773008743358055,
    "dix": 0.42,
    "vanna": -206.62886761581663,
    "charm": -3230.7674624154506
  },
  "flow_metrics": {
    "gex": 16.773008743358055,
    "dix": 0.42,
    "vanna": -206.62886761581663,
    "charm": -3230.7674624154506
  },
  "metrics": {
    "vix": 20.76038753855593,
    "rsi": 58.88627186989923,
    "macd": {
      "value": 0.4829181641992599,
      "signal": 0.037140818790306396,
      "histogram": 0.2450269327844135
    },
    "gex": 16.773008743358055,
    "darkPoolBias": -0.005440265507585362
  }
}